prowlpy/__init__.py
prowlpy/_cli.py
prowlpy/prowlpy.py
prowlpy/py.typed
prowlpy-1.1.3.dist-info/licenses/LICENSE
prowlpy-1.1.3.dist-info/METADATA
prowlpy-1.1.3.dist-info/WHEEL
prowlpy-1.1.3.dist-info/entry_points.txt
prowlpy-1.1.3.dist-info/top_level.txt
prowlpy-1.1.3.dist-info/RECORD
