Metadata-Version: 2.4
Name: prowlpy
Version: 1.1.3
Summary: Prowlpy is a python library that implements the public api of Prowl to send push notification to iPhones.
Author: OMEGA_RAZER
License-Expression: GPL-3.0-only
Project-URL: Homepage, https://omegarazer.github.io/prowlpy
Project-URL: Source, https://github.com/OMEGARAZER/prowlpy
Project-URL: Bug Reports, https://github.com/OMEGARAZER/prowlpy/issues
Keywords: prowl,push,notification,iphone
Classifier: Development Status :: 5 - Production/Stable
Classifier: Operating System :: OS Independent
Classifier: Programming Language :: Python :: 3
Classifier: Programming Language :: Python :: 3.10
Classifier: Programming Language :: Python :: 3.11
Classifier: Programming Language :: Python :: 3.12
Classifier: Programming Language :: Python :: 3.13
Classifier: Programming Language :: Python :: 3.14
Requires-Python: >=3.10
License-File: LICENSE
Requires-Dist: httpx[http2]>=0.23.0
Requires-Dist: xmltodict>=0.13.0
Provides-Extra: cli
Requires-Dist: click>=8.1.0; extra == "cli"
Requires-Dist: loguru>=0.6.0; extra == "cli"
Dynamic: license-file
